public final class BKt {
public static final java.lang.String box();
Code:
iconst_5
newarray int
astore_0
iconst_0
istore_1
aload_0
arraylength
istore_2
iload_1
iload_2
if_icmpge 48
aload_0
iload_1
iaload
istore_3
iload_3
ifeq 42
new // class java/lang/StringBuilder
dup
invokespecial // Method java/lang/StringBuilder."<init>":()V
ldc // String Fail
invokevirtual // Method java/lang/StringBuilder.append:(Ljava/lang/String;)Ljava/lang/StringBuilder;
iload_3
invokevirtual // Method java/lang/StringBuilder.append:(I)Ljava/lang/StringBuilder;
invokevirtual // Method java/lang/StringBuilder.toString:()Ljava/lang/String;
areturn
iinc 1, 1
goto 9
ldc // String OK
areturn
}
